hardware/CPLD Project/MSXInterface.vhd
-- Ronivon Candido Costa
-- 22/10/2016
-- MSX_Interface using new proto board
-- Receives 8 bits on D bus, convert to serial and send to external IO (SPI pins)
----------------------------------------------------------------------------------
-- CPLD: V0.5
-- MSX: bootv5.bin
-- Pi: msx.c (v1.5)
----------------------------------------------------------------------------------
-- Version 0.5
-- For prototype 2, with Pi Zero attached on the cart.
-- Ports:
-- 07 - Data (read/write data)
-- 06 - Control:
--          (Write) 0xFF - Reset
--          (Write) 0x00 - Read command
--          (Read)       - SPI status, 0 = busy, 1 = data ready
--          
----------------------------------------------------------------------------------
-- version 0.6
-- Added signal RDY to control data flow between MSX,CPLD and Pi.
-- SPI_RDY Low  = Ready
-- SPI_RDY HIGH = Busy
----------------------------------------------------------------------------------
-- version 0.7
-- Added signal BUSDIR
----------------------------------------------------------------------------------
-- Version 0.7 Rev 4 - 2017-07-22
-- Added package msxpi_package with PORTS definition
-- Modified ports (from 6,7,8) to range 0x56 - 0x5D
----------------------------------------------------------------------------------
-- Version 0.9 Rev 0 - 2020-07-10
-- Removed package msxpi_package with PORTS definition - why I added by the way?
-- Replaced BUSDIR by WAIT. Needs mod in the interface
-- Added CPLD suppport for /WAIT signal, still compatible with previous versions
----------------------------------------------------------------------------------
-- MSXPi PCB revisions supported by this design:
-- 
-- 0001: Wired up prototype, without EPROM,EPM3064ALC-44
-- 0010: Semi-wired up prototype, with EPROM, EPM3064ATC-44
-- 0011: Limited 10-samples PCB, with EPROM, EPM3064ALC-44
-- 0100: Limited 1 sample PCB, with EPROM, EPM3064ALC-44, 4 bits mode.
-- 0101: Limited 10 samples PCB Rev.3, EPROM, EPM3064ALC-44
-- 0110: Wired up prototype, with EPROM, EPM7128SLC-84
-- 0111: Rev.4 batch, EPM3064ALC-44 (First public release)
-- 1000: Limited 10 samples, Big v0.8.1 Rev.0, EPM7128SLC-84, not released
-- 1001: Rev.4 or later with /Wait mod, with EPROM, EPM3064ALC-44
--
-- ----------------------------------------------------------------------------------
library ieee ;
use ieee.std_logic_1164.all; 
use ieee.numeric_std.all;
--use work.msxpi_package.all;

ENTITY MSXInterface IS
PORT ( 
    D           : INOUT STD_LOGIC_VECTOR(7 DOWNTO 0);
    A           : IN STD_LOGIC_VECTOR(7 DOWNTO 0);
    IORQ_n      : IN STD_LOGIC;
    RD_n        : IN STD_LOGIC;
    WR_n        : IN STD_LOGIC;
    WAIT_n      : OUT STD_LOGIC;
    --
    SPI_CS      : OUT STD_LOGIC;
    SPI_SCLK    : IN STD_LOGIC;
    SPI_MOSI    : OUT STD_LOGIC;
    SPI_MISO    : IN STD_LOGIC;
    SPI_RDY     : IN STD_LOGIC;
    --
    LED         : OUT STD_LOGIC);
END MSXInterface;

architecture rtl of MSXInterface is

    constant MSXPIVer   : STD_LOGIC_VECTOR(3 DOWNTO 0) := "1001";
    constant DATAPORT   : STD_LOGIC_VECTOR(7 downto 0) := x"5A";
    constant CTRLPORT1  : STD_LOGIC_VECTOR(7 downto 0) := x"5B";
    constant CTRLPORT2  : STD_LOGIC_VECTOR(7 downto 0) := x"5C";

    
    
    type fsm_type is (start,transferring);
    signal state : fsm_type := start;
    
    signal readoper_s     : std_logic;
    signal writeoper_s    : std_logic;
    signal rpi_en_s       : std_logic;
    signal D_buff_msx_s   : std_logic_vector(7 downto 0);
    signal D_buff_pi_s    : std_logic_vector(7 downto 0);  
    signal wait_n_s       : std_logic := 'Z';
    signal rpi_enabled_s  : std_logic := '0';
    --signal msxpi_status_s : std_logic;
	
	signal D_buff_pi_debug_s    : std_logic_vector(7 downto 0);
	
begin

    LED    <= rpi_enabled_s;
    SPI_CS <= not rpi_enabled_s;
    WAIT_n <= wait_n_s;

    --WAIT_n <= '0' when state = transferring else
	--           '0' when SPI_MISO = '0' else 'Z';
    
	 --   msxpi_status_s <= "00" when SPI_MISO = '1' and rpi_enabled_s = '0' else
     --                  "01" when SPI_MISO = '0' and rpi_enabled_s = '0' else
     --                       "10";

    readoper_s  <= not (IORQ_n or RD_n);
    writeoper_s <= not (IORQ_n or WR_n);
    rpi_en_s    <= '1' when (A = DATAPORT and (writeoper_s = '1' or readoper_s = '1')) else '0';

    D <= "0000000" & (not SPI_MISO) when (readoper_s = '1' and A = CTRLPORT1) else   
         D_buff_pi_s when readoper_s = '1' and A = DATAPORT else
         "0000" & MSXPIVer when (readoper_s = '1' and A = CTRLPORT2) else 
         "ZZZZZZZZ";

    -- Triggers the interface
    process(rpi_en_s, SPI_RDY)
    begin
        if (SPI_RDY = '0') then
            rpi_enabled_s <= '0';
            wait_n_s <= 'Z';
        elsif (rising_edge(rpi_en_s)) then
            wait_n_s <= '0';
            rpi_enabled_s <= '1';
         end if;
    end process;

    -- Initialize serial/paralell process
    process(rpi_enabled_s,rpi_en_s,SPI_SCLK)
    begin
        if (rpi_enabled_s = '0') then
            state <= start;
        elsif rising_edge(SPI_SCLK) then
            state <= transferring;
        end if;
    end process;
    
    -- Convert MSX data to serial / RPi serial to paralell
    -- Send bits to RPi in serial mode, receive RPi bits and latches
    process(SPI_SCLK)
	variable mosi_debug: std_logic_vector(7 downto 0);
    begin
         if (state = start) then
            D_buff_msx_s <= D;
        elsif rising_edge(SPI_SCLK) then
            D_buff_pi_s <= D_buff_pi_s(6 downto 0) & SPI_MISO;
            SPI_MOSI <= D_buff_msx_s(7);
			
			-- debug
			mosi_debug := mosi_debug(6 downto 0) & D_buff_msx_s(7);
			--
			
            D_buff_msx_s(7 downto 1) <= D_buff_msx_s(6 downto 0);			
        end if;
		
		D_buff_pi_debug_s <= mosi_debug;
		
    end process;
end rtl;

hardware/CPLD Project/MSXInterface_tb.vhd
library ieee ;
use ieee.std_logic_1164.all; 
use ieee.numeric_std.all;

entity MSXInterface_tb is
end MSXInterface_tb;

architecture tb of MSXInterface_tb is
	component MSXInterface is
		port (
			d			: inout std_logic_vector(7 downto 0);
			a			: in std_logic_vector(7 downto 0);
			iorq_n		: in std_logic;
			rd_n		: in std_logic;
			wr_n		: in std_logic;
			wait_n		: out std_logic;
			spi_cs		: out std_logic;
			spi_sclk	: in std_logic;
			spi_mosi	: out std_logic;
			spi_miso	: in std_logic;
			spi_rdy  	: in std_logic;
			led			: out std_logic);
	end component;

	constant bus_size : integer := 16; -- Address + Data sizes
	constant bus_control_size : integer := 3;
	
	type state_type is (idle, prepare_spi, send_bus_data, receive_bus_data);
	signal spi_state, next_state	: state_type := idle;	

	signal a_s		 	: std_logic_vector(7 downto 0);
	signal d_s	 	    : std_logic_vector(7 downto 0);
	signal iorq_n_s		: std_logic;
	signal rd_n_s		: std_logic;
	signal wr_n_s		: std_logic;
	signal wait_n_s		: std_logic;
	signal spi_cs_s 	: std_logic;
	signal spi_clk_s	: std_logic;
	signal spi_mosi_s	: std_logic;
	signal spi_miso_s	: std_logic;
	signal rpi_rdy_s	: std_logic;
	signal led_s		: std_logic;

begin

	msxpi_instance: MSXInterface
		port map(
			d => d_s,
			a => a_s,
			iorq_n => iorq_n_s,
			rd_n => rd_n_s,
			wr_n => wr_n_s,
			wait_n => wait_n_s,
			spi_cs => spi_cs_s,
			spi_sclk => spi_clk_s,
			spi_mosi => spi_mosi_s,
			spi_miso => spi_miso_S,
			spi_rdy => rpi_rdy_s,
			led => led_s);

	process
	begin

		spi_clk_s <= 'U';
		wr_n_s <= 'U';
		rd_n_s <= 'U';
		iorq_n_s <= 'U';
		rpi_rdy_s <= '0';
		wait for 10 fs;
		rpi_rdy_s <= '1';
		spi_miso_s <= '0';
		wait for 10 fs;
				
		a_s <= x"5A";
		d_s <= x"BC";
		wr_n_s <= '0';
		rd_n_s <= '1';
		iorq_n_s <= '0';
		wait for 10 fs;
		
		spi_miso_s <= '1';
		wait for 10 fs;

		spi_clk_s <= '1';
		wait for 10 fs;
		spi_clk_s <= '0';	
		wait for 10 fs;
		
		-- read 8 bits of data from RPi
		-- simulate RPi taking its time to prepare data

		spi_clk_s <= '1';
		wait for 10 fs;
		spi_miso_s <= '1';
		spi_clk_s <= '0';
		wait for 10 fs;

		spi_clk_s <= '1';
		wait for 10 fs;
		spi_miso_s <= '0';
		spi_clk_s <= '0';
		wait for 10 fs;

		spi_clk_s <= '1';
		wait for 10 fs;
		spi_miso_s <= '1';
		spi_clk_s <= '0';
		wait for 10 fs;

		spi_clk_s <= '1';
		wait for 10 fs;
		spi_miso_s <= '0';
		spi_clk_s <= '0';
		wait for 10 fs;

		spi_clk_s <= '1';
		wait for 10 fs;
		spi_miso_s <= '1';
		spi_clk_s <= '0';
		wait for 10 fs;

		spi_clk_s <= '1';
		wait for 10 fs;
		spi_miso_s <= '0';
		spi_clk_s <= '0';
		wait for 10 fs;

		spi_clk_s <= '1';
		wait for 10 fs;
		spi_miso_s <= '1';
		spi_clk_s <= '0';
		wait for 10 fs;

		spi_clk_s <= '1';
		wait for 10 fs;
		spi_miso_s <= '0';
		spi_clk_s <= '0';
		wait for 10 fs;

		rpi_rdy_s <= '0';
		spi_miso_s <= '0';
		wait for 10 fs;
		rpi_rdy_s <= '1';

		wait for 10 fs;
		wr_n_s <= '1';
		rd_n_s <= '1';	
		iorq_n_s <= '1';
		
		wait for 50 fs;
		
	-- Send data to RPi
	-- 8 bits for address, 8 bits for data, wr, rd, iorq = 19 bits
	-- Start transfer cycle

		wait for 10 fs;
		wr_n_s <= '1';
		iorq_n_s <= '0';
		rd_n_s <= '0';	
		
		spi_mosi_s <= '1';
		spi_clk_s <= '1';
		wait for 10 fs;
		spi_clk_s <= '0';
		wait for 10 fs;

		spi_mosi_s <= '0';
		spi_clk_s <= '1';
		wait for 10 fs;
		spi_clk_s <= '0';
		wait for 10 fs;

		spi_mosi_s <= '1';
		spi_clk_s <= '1';
		wait for 10 fs;
		spi_clk_s <= '0';
		wait for 10 fs;

		spi_mosi_s <= '0';
		spi_clk_s <= '1';
		wait for 10 fs;
		spi_clk_s <= '0';
		wait for 10 fs;

		spi_mosi_s <= '1';
		spi_clk_s <= '1';
		wait for 10 fs;
		spi_clk_s <= '0';
		wait for 10 fs;

		spi_mosi_s <= '0';
		spi_clk_s <= '1';
		wait for 10 fs;
		spi_clk_s <= '0';
		wait for 10 fs;

		spi_mosi_s <= '1';
		spi_clk_s <= '1';
		wait for 10 fs;
		spi_clk_s <= '0';
		wait for 10 fs;

		spi_mosi_s <= '0';
		spi_clk_s <= '1';
		wait for 10 fs;
		spi_clk_s <= '0';
		wait for 10 fs;
	
		rpi_rdy_s <= '0';
		spi_miso_s <= '0';
		wait for 10 fs;
		rpi_rdy_s <= '1';

		wait for 10 fs;
		wr_n_s <= '1';
		iorq_n_s <= '1';
		rd_n_s <= '1';	
		
		wait for 50 fs;
		
		wait;

	end process;
end;

hardware/CPLD Project/MSXInterface.vcd
$date
  Thu Jul 30 00:49:03 2020
$end
$version
  GHDL v0
$end
$timescale
  1 fs
$end
$scope module standard $end
$upscope $end
$scope module std_logic_1164 $end
$upscope $end
$scope module numeric_std $end
$upscope $end
$scope module msxinterface_tb $end
$comment spi_state is not handled $end
$comment next_state is not handled $end
$var reg 8 ! a_s[7:0] $end
$var reg 8 " d_s[7:0] $end
$var reg 1 # iorq_n_s $end
$var reg 1 $ rd_n_s $end
$var reg 1 % wr_n_s $end
$var reg 1 & wait_n_s $end
$var reg 1 ' spi_cs_s $end
$var reg 1 ( spi_clk_s $end
$var reg 1 ) spi_mosi_s $end
$var reg 1 * spi_miso_s $end
$var reg 1 + rpi_rdy_s $end
$var reg 1 , led_s $end
$scope module msxpi_instance $end
$var reg 8 - d[7:0] $end
$var reg 8 . a[7:0] $end
$var reg 1 / iorq_n $end
$var reg 1 0 rd_n $end
$var reg 1 1 wr_n $end
$var reg 1 2 wait_n $end
$var reg 1 3 spi_cs $end
$var reg 1 4 spi_sclk $end
$var reg 1 5 spi_mosi $end
$var reg 1 6 spi_miso $end
$var reg 1 7 spi_rdy $end
$var reg 1 8 led $end
$comment state is not handled $end
$var reg 1 9 readoper_s $end
$var reg 1 : writeoper_s $end
$var reg 1 ; rpi_en_s $end
$var reg 8 < d_buff_msx_s[7:0] $end
$var reg 8 = d_buff_pi_s[7:0] $end
$var reg 1 > wait_n_s $end
$var reg 1 ? rpi_enabled_s $end
$var reg 8 @ d_buff_pi_debug_s[7:0] $end
$upscope $end
$upscope $end
$enddefinitions $end
#0
bUUUUUUUU !
bUUUUUUUU "
U#
U$
U%
Z&
1'
U(
U)
U*
0+
0,
bUUUUUUUU -
bUUUUUUUU .
U/
U0
U1
Z2
13
U4
U5
U6
07
08
U9
U:
0;
bUUUUUUUU <
bUUUUUUUU =
Z>
0?
bUUUUUUUU @
#10
0*
1+
06
17
#20
b01011010 !
b10111100 "
0#
1$
0%
0&
0'
1,
b10111100 -
b01011010 .
0/
10
01
02
03
18
09
1:
1;
0>
1?
#30
1*
16
#40
1(
14
b10111100 <
#50
0(
04
#60
1(
14
#70
0(
04
#80
1(
14
U5
b01111000 <
bUUUUUUU1 =
bUUUUUUU1 @
#90
0(
0*
04
06
#100
1(
14
U5
b11110000 <
bUUUUUU10 =
bUUUUUU10 @
#110
0(
1*
04
16
#120
1(
14
U5
b11100000 <
bUUUUU101 =
bUUUUU101 @
#130
0(
0*
04
06
#140
1(
14
U5
b11000000 <
bUUUU1010 =
bUUUU1011 @
#150
0(
1*
04
16
#160
1(
14
U5
b10000000 <
bUUU10101 =
bUUU10111 @
#170
0(
0*
04
06
#180
1(
14
U5
b00000000 <
bUU101010 =
bUU101111 @
#190
0(
1*
04
16
#200
1(
14
U5
bU1010101 =
bU1011110 @
#210
0(
0*
04
06
#220
Z&
1'
0+
0,
Z2
13
07
08
Z>
0?
#230
1+
17
#240
1#
1%
1/
11
0:
0;
#290
#300
bUXX1X10X "
0#
0$
0&
0'
1(
X)
1,
bUXX1X10X -
0/
00
02
03
14
X5
18
19
1;
b10111100 <
0>
1?
#310
0(
04
bUXX1X10X <
#320
1(
0)
14
05
#330
0(
04
#340
b101X1XX0 "
1(
U)
b101X1XX0 -
14
U5
bXX1X10XX <
b10101010 =
b1011110U @
#350
0(
04
#360
bXXX1X100 "
1(
X)
bXXX1X100 -
14
X5
bX1X10XXX <
b01010100 =
b011110UX @
#370
0(
04
#380
b101X1X00 "
1(
b101X1X00 -
14
X5
b1X10XXXX <
b10101000 =
b11110UXX @
#390
0(
04
#400
bXXX1XX00 "
1(
bXXX1XX00 -
14
X5
bX10XXXXX <
b01010000 =
b1110UXX1 @
#410
0(
04
#420
b101XXX00 "
1(
X)
b101XXX00 -
14
X5
b10XXXXXX <
b10100000 =
b110UXX1X @
#430
0(
04
#440
bXXXXXX00 "
1(
bXXXXXX00 -
14
X5
b0XXXXXXX <
b01000000 =
b10UXX1X1 @
#450
0(
04
#460
Z&
1'
0+
0,
Z2
13
07
08
Z>
0?
#470
1+
17
#480
b10111100 "
1#
1$
b10111100 -
1/
10
09
0;
