hardware/CPLD_Project/MSXPi.vhd
-- Ronivon Candido Costa
-- 22/10/2016
-- MSX_Interface using new proto board
-- Receives 8 bits on D bus, convert to serial and send to external IO (SPI pins)
----------------------------------------------------------------------------------
-- CPLD: V0.5
-- MSX: bootv5.bin
-- Pi: msx.c (v1.5)
----------------------------------------------------------------------------------
-- Version 0.5
-- For prototype 2, with Pi Zero attached on the cart.
-- Ports:
-- 07 - Data (read/write data)
-- 06 - Control:
--          (Write) 0xFF - Reset
--          (Write) 0x00 - Read command
--          (Read)       - SPI status, 0 = busy, 1 = data ready
--          
----------------------------------------------------------------------------------
-- version 0.6
-- Added signal RDY to control data flow between MSX,CPLD and Pi.
-- SPI_RDY Low  = Ready
-- SPI_RDY HIGH = Busy
--
----------------------------------------------------------------------------------
-- version 0.7
-- Added signal BUSDIR
----------------------------------------------------------------------------------
-- Version 0.7 Rev 4 - 2017-07-22
-- Added package msxpi_package with PORTS definition
-- Modified ports (from 6,7,8) to range 0x56 - 0x5D
----------------------------------------------------------------------------------
-- Version 1.0 Rev 0 - 2020-08-01
-- Added support to /Wait signal (using LED pin)
-- LED now is drived by SPI_CS signal
----------------------------------------------------------------------------------
-- MSXPI Versions:
-- 0001: Wired up prototype, EPM3064ALC-44
-- 0010: Semi-wired up prototype, EPROM 27C256, EPM3064ATC-44
-- 0011: Limited 10-samples PCB, EPROM 27C256, EPM3064ALC-44
-- 0100: Limited 1 sample PCB, EPROM 27C256, EPM3064ALC-44, 4 bits mode.
-- 0101: Limited 10 samples PCB Rev.3, EPROM 27C256, EPM3064ALC-44
-- 0110: Wired up prototype, EPROM 27C256, EPM7128SLC-84
-- 0111: General Release V0.7 Rev.4, EPROM 27C256, EPM3064ALC-44
-- 1000: Prototype 10 samples, Big v0.8.1 Rev.0, EPM7128SLC-84
-- 1001: General Release V1.0 Rev 0, EPROM 27C256, EPM3064ALC-44
-- 1010: General Release V1.1 Rev 0, EEPROM AT28C256, EPM3064ALC-44
-- ----------------------------------------------------------------------------------
library ieee ;
use ieee.std_logic_1164.all; 
use ieee.numeric_std.all;
--use IEEE.STD_LOGIC_UNSIGNED.ALL;

ENTITY MSXPi IS
PORT ( 
    D           : INOUT STD_LOGIC_VECTOR(7 DOWNTO 0);
    A           : IN STD_LOGIC_VECTOR(7 DOWNTO 0);
    IORQ_n      : IN STD_LOGIC;
    RD_n        : IN STD_LOGIC;
    WR_n        : IN STD_LOGIC;
    BUSDIR_n    : OUT STD_LOGIC;
    WAIT_n      : OUT STD_LOGIC;
    --
    SPI_CS      : OUT STD_LOGIC;
    SPI_SCLK    : IN STD_LOGIC;
    SPI_MOSI    : OUT STD_LOGIC;
    SPI_MISO    : IN STD_LOGIC;
    SPI_RDY     : IN STD_LOGIC);
END MSXPi;



architecture rtl of MSXPi is
constant MSXPIVer : STD_LOGIC_VECTOR(3 DOWNTO 0) := "1001";
constant CTRLPORT1: STD_LOGIC_VECTOR(7 downto 0) := x"56";
constant CTRLPORT2: STD_LOGIC_VECTOR(7 downto 0) := x"57";
constant CTRLPORT3: STD_LOGIC_VECTOR(7 downto 0) := x"58";
constant CTRLPORT4: STD_LOGIC_VECTOR(7 downto 0) := x"59";
constant DATAPORT1: STD_LOGIC_VECTOR(7 downto 0) := x"5A";
constant DATAPORT2: STD_LOGIC_VECTOR(7 downto 0) := x"5B";
constant DATAPORT3: STD_LOGIC_VECTOR(7 downto 0) := x"5C";
constant DATAPORT4: STD_LOGIC_VECTOR(7 downto 0) := x"5D";

    signal csPin			: std_logic;

	signal D_buff_pi		: std_logic_vector(7 downto 0);
	signal RESET			: std_logic;
	signal D_buff_msx		: std_logic_vector(7 downto 0);
	signal waitSignal		: STD_LOGIC := 'Z';
	signal msxwrite_s		: STD_LOGIC;
	signal msxread_s		: STD_LOGIC;
	signal spi_count_s	: std_logic_vector(3 downto 0) := "0000";
    
begin
  
	SPI_CS <= csPin;
	msxwrite_s <= IORQ_n or WR_n;
	msxread_s <= IORQ_n or RD_n;
	WAIT_n <= 'Z';
	D_buff_msx <= D when msxwrite_s = '0' and A = DATAPORT1;
	D <= D_buff_pi when msxread_s = '0' and A = DATAPORT1 and SPI_RDY = '1' else
        SPI_RDY & csPin & "00" & MSXPIVer when msxread_s = '0' and A = DATAPORT1 and SPI_RDY = '0' else
		  "ZZZZZZZZ";
	      
process(IORQ_n, WR_n, RD_n, waitSignal, SPI_RDY,spi_count_s)
begin
	if spi_count_s > "1001" then 
         csPin	<= '1';														-- Enable RPi for data transfer
         waitSignal <= '1';												-- Enable Wait state in MSX - make it wait
	elsif (csPin = '1' and IORQ_n = '0' and (WR_n = '0' or RD_n = '0')) then		-- a new read/write request from MSX
																					-- SPI_RDY = 0 -> RPi ready for new commands
        csPin <= '0';														-- Disable RPi transfers
        waitSignal <= '0';													-- Disble Wait state in MSX
	elsif csPin = '1' then												-- Check if Wait transitioned from 0 to 1
		waitSignal <= 'Z';													-- Put Wait in tri-state
	end if;

end process;

process(SPI_SCLK)
variable D_reg : std_logic_vector(7 downto 0) := "00000000";
begin
	if rising_edge(SPI_SCLK) then
		if spi_count_s = "0000" then
			D_reg := D_buff_msx;
		else
			D_buff_pi <= D_buff_pi(6 downto 0) & SPI_MISO;
			SPI_MOSI <= D_reg(7);
			D_reg(7 downto 1) := D_reg(6 downto 0);
		end if;
	end if;
end process;

process(SPI_SCLK)
begin
	if rising_edge(SPI_SCLK) then
		if spi_count_s > "1001" then
			spi_count_s <= "0000";
		else
			spi_count_s <= std_logic_vector(to_unsigned(to_integer(unsigned(spi_count_s)) + 1, 4));
		end if;
	end if;
end process;

end rtl;

hardware/CPLD_Project/Sim/msxpi_tb.vhd
library ieee ;
use ieee.std_logic_1164.all; 
use ieee.numeric_std.all;

entity msxpi_tb is
end msxpi_tb;

architecture tb of msxpi_tb is
	component MSXPi is
		port (
			d			: inout std_logic_vector(7 downto 0);
			a			: in std_logic_vector(7 downto 0);
			iorq_n		: in std_logic;
			rd_n		: in std_logic;
			wr_n		: in std_logic;
			wait_n		: out std_logic;
			busdir_n	: out std_logic;
			spi_cs		: out std_logic;
			spi_sclk	: in std_logic;
			spi_mosi	: out std_logic;
			spi_miso	: in std_logic;
			spi_rdy  	: in std_logic);
	end component;

	signal a_s		 	: std_logic_vector(7 downto 0);
	signal d_s	 	    : std_logic_vector(7 downto 0);
	signal iorq_n_s		: std_logic;
	signal rd_n_s		: std_logic;
	signal wr_n_s		: std_logic;
	signal wait_n_s		: std_logic;
	signal busdir_n_s	: std_logic;
	signal spi_cs_s 	: std_logic;
	signal spi_clk_s	: std_logic;
	signal spi_mosi_s	: std_logic;
	signal spi_miso_s	: std_logic;
	signal rpi_rdy_s	: std_logic;

begin

	msxpi_instance: MSXPi
		port map(
			d => d_s,
			a => a_s,
			iorq_n => iorq_n_s,
			rd_n => rd_n_s,
			wr_n => wr_n_s,
			wait_n => wait_n_s,
			busdir_n => busdir_n_s,
			spi_cs => spi_cs_s,
			spi_sclk => spi_clk_s,
			spi_mosi => spi_mosi_s,
			spi_miso => spi_miso_S,
			spi_rdy => rpi_rdy_s);

	process
	begin
		
		spi_clk_s <= 'U';
		wr_n_s <= 'U';
		rd_n_s <= 'U';
		iorq_n_s <= 'U';
		rpi_rdy_s <= '0';
		wait for 2 ns;
		
		rpi_rdy_s <= '0';
		a_s <= x"5A";
		d_s <= x"AE";
		wr_n_s <= '0';
		rd_n_s <= '1';
		iorq_n_s <= '0';
		wait for 2 ns;

		rpi_rdy_s <= '1';
		wait for 2 ns;
		
		spi_clk_s <= '1';
		wait for 2 ns;

		spi_clk_s <= '0';
		wait for 2 ns;

		spi_clk_s <= '1';
		wait for 2 ns;

		spi_clk_s <= '0';
		wait for 2 ns;
		
		spi_clk_s <= '1';
		wait for 2 ns;

		spi_clk_s <= '0';
		wait for 2 ns;
		
		spi_clk_s <= '1';
		wait for 2 ns;

		spi_clk_s <= '0';
		wait for 2 ns;

		spi_clk_s <= '1';
		wait for 2 ns;

		spi_clk_s <= '0';
		wait for 2 ns;

		spi_clk_s <= '1';
		wait for 2 ns;

		spi_clk_s <= '0';
		wait for 2 ns;
		
		spi_clk_s <= '1';
		wait for 2 ns;

		spi_clk_s <= '0';
		wait for 2 ns;
		
		spi_clk_s <= '1';
		wait for 2 ns;

		spi_clk_s <= '0';
		wait for 2 ns;
	
		spi_clk_s <= '1';
		wait for 2 ns;

		spi_clk_s <= '0';
		wait for 2 ns;
		
		spi_clk_s <= '1';
		wait for 2 ns;

		spi_clk_s <= '0';
		wait for 2 ns;
		
		spi_clk_s <= '1';
		wait for 2 ns;

		spi_clk_s <= '0';
		wait for 2 ns;
						
		rpi_rdy_s <= '0';
		wait for 2 ns;
		
		spi_clk_s <= '1';
		wait for 2 ns;

		spi_clk_s <= '0';
		wait for 2 ns;
	
-- end of byte transfer - RPi signal free rising SPI_RDY
		rpi_rdy_s <= '0';
		wr_n_s <= '0';
		rd_n_s <= '1';
		iorq_n_s <= '1';
		wait for 2 ns;
		
-- end of test bench

		wait for 200 ns;
		
		wait;

	end process;
end;

hardware/CPLD_Project/Sim/msxpi_tb.vcd
$date
  Wed Dec 21 20:26:44 2022
$end
$version
  GHDL v0
$end
$timescale
  1 fs
$end
$scope module standard $end
$upscope $end
$scope module std_logic_1164 $end
$upscope $end
$scope module numeric_std $end
$upscope $end
$scope module msxpi_tb $end
$var reg 8 ! a_s[7:0] $end
$var reg 8 " d_s[7:0] $end
$var reg 1 # iorq_n_s $end
$var reg 1 $ rd_n_s $end
$var reg 1 % wr_n_s $end
$var reg 1 & wait_n_s $end
$var reg 1 ' busdir_n_s $end
$var reg 1 ( spi_cs_s $end
$var reg 1 ) spi_clk_s $end
$var reg 1 * spi_mosi_s $end
$var reg 1 + spi_miso_s $end
$var reg 1 , rpi_rdy_s $end
$scope module msxpi_instance $end
$var reg 8 - d[7:0] $end
$var reg 8 . a[7:0] $end
$var reg 1 / iorq_n $end
$var reg 1 0 rd_n $end
$var reg 1 1 wr_n $end
$var reg 1 2 busdir_n $end
$var reg 1 3 wait_n $end
$var reg 1 4 spi_cs $end
$var reg 1 5 spi_sclk $end
$var reg 1 6 spi_mosi $end
$var reg 1 7 spi_miso $end
$var reg 1 8 spi_rdy $end
$var reg 1 9 cspin $end
$var reg 8 : d_buff_pi[7:0] $end
$var reg 1 ; reset $end
$var reg 8 < d_buff_msx[7:0] $end
$var reg 1 = waitsignal $end
$var reg 1 > msxwrite_s $end
$var reg 1 ? msxread_s $end
$var reg 4 @ spi_count_s[3:0] $end
$upscope $end
$upscope $end
$enddefinitions $end
#0
bUUUUUUUU !
bUUUUUUUU "
U#
U$
U%
Z&
U'
U(
U)
U*
U+
0,
bUUUUUUUU -
bUUUUUUUU .
U/
U0
U1
U2
Z3
U4
U5
U6
U7
08
U9
bUUUUUUUU :
U;
bUUUUUUUU <
Z=
U>
U?
b0000 @
#2000000
b01011010 !
b10101110 "
0#
1$
0%
b10101110 -
b01011010 .
0/
10
01
b10101110 <
0>
1?
#4000000
1,
18
#6000000
1)
15
#8000000
0)
05
#10000000
1)
15
b0001 @
#12000000
0)
05
#14000000
1)
1*
15
16
b0010 @
#16000000
0)
05
#18000000
1)
0*
15
06
b0011 @
#20000000
0)
05
#22000000
1)
1*
15
16
b0100 @
#24000000
0)
05
#26000000
1)
0*
15
06
b0101 @
#28000000
0)
05
#30000000
1)
1*
15
16
b0110 @
#32000000
0)
05
#34000000
1)
15
b0111 @
#36000000
0)
05
#38000000
1)
15
b1000 @
#40000000
0)
05
#42000000
1)
0*
15
06
b1001 @
#44000000
0)
05
#46000000
1(
1)
14
15
19
1=
b1010 @
#48000000
0)
05
#50000000
0,
08
#52000000
0(
1)
04
15
09
0=
b0000 @
#54000000
0)
05
#56000000
1#
1/
1>
