hardware/CPLD_Project/MSXPi.vhd
-- Ronivon Candido Costa
-- 22/10/2016
-- MSX_Interface using new proto board
-- Receives 8 bits on D bus, convert to serial and send to external IO (SPI pins)
----------------------------------------------------------------------------------
-- CPLD: V0.5
-- MSX: bootv5.bin
-- Pi: msx.c (v1.5)
----------------------------------------------------------------------------------
-- Version 0.5
-- For prototype 2, with Pi Zero attached on the cart.
-- Ports:
-- 07 - Data (read/write data)
-- 06 - Control:
--          (Write) 0xFF - Reset
--          (Write) 0x00 - Read command
--          (Read)       - SPI status, 0 = busy, 1 = data ready
--          
----------------------------------------------------------------------------------
-- version 0.6
-- Added signal RDY to control data flow between MSX,CPLD and Pi.
-- SPI_RDY Low  = Ready
-- SPI_RDY HIGH = Busy
--
----------------------------------------------------------------------------------
-- version 0.7
-- Added signal BUSDIR
----------------------------------------------------------------------------------
-- Version 0.7 Rev 4 - 2017-07-22
-- Added package msxpi_package with PORTS definition
-- Modified ports (from 6,7,8) to range 0x56 - 0x5D
----------------------------------------------------------------------------------
-- Version 1.0 Rev 0 - 2020-08-01
-- Added support to /Wait signal (using LED pin)
-- LED now is drived by SPI_CS signal
----------------------------------------------------------------------------------
-- Version 1.0.1 - 2022-12-21
-- Redesigned the CPLD firmware / code
-- Serial protocol - MSX Reading data:
--	
--		Enable SPI_CS - '0'
--		Enable MSX /Wait - '0'
--		RPi Disable SPI_RDY - '1'
--		Wait RPi clock rising event on pin SPI_SCLK
--		1st Tick is for sync, no valid data present in SPI_MISO
--    Next 8 Ticks contain 8 bits of data in SPI_MISO
--		Move Data to Latch D - ready for MSX D register
--    1 Tick for sync / cleanup
-- 	RPi Enable SPY_RDY - '0'
--		Disable SPI_CS - '1'
--		Disable MSX /Wait - 'Z'
----------------------------------------------------------------------------------

-- MSXPI Versions:
-- 0001: Wired up prototype, EPM3064ALC-44
-- 0010: Semi-wired up prototype, EPROM 27C256, EPM3064ATC-44
-- 0011: Limited 10-samples PCB, EPROM 27C256, EPM3064ALC-44
-- 0100: Limited 1 sample PCB, EPROM 27C256, EPM3064ALC-44, 4 bits mode.
-- 0101: Limited 10 samples PCB Rev.3, EPROM 27C256, EPM3064ALC-44
-- 0110: Wired up prototype, EPROM 27C256, EPM7128SLC-84
-- 0111: General Release V0.7 Rev.4, EPROM 27C256, EPM3064ALC-44
-- 1000: Prototype 10 samples, Big v0.8.1 Rev.0, EPM7128SLC-84
-- 1001: General Release V1.0 Rev 0, EPROM 27C256, EPM3064ALC-44
-- 1010: General Release V1.1 Rev 0, EEPROM AT28C256, EPM3064ALC-44
-- 1011: General Release V1.0.1, EEPROM AT28C256, EPM3064ALC-44
-- ----------------------------------------------------------------------------------
library ieee ;
use ieee.std_logic_1164.all; 
use ieee.numeric_std.all;
--use IEEE.STD_LOGIC_UNSIGNED.ALL;

ENTITY MSXPi IS
PORT ( 
    D           : INOUT STD_LOGIC_VECTOR(7 DOWNTO 0);
    A           : IN STD_LOGIC_VECTOR(7 DOWNTO 0);
    IORQ_n      : IN STD_LOGIC;
    RD_n        : IN STD_LOGIC;
    WR_n        : IN STD_LOGIC;
    BUSDIR_n    : OUT STD_LOGIC;
    WAIT_n      : OUT STD_LOGIC;
    --
    SPI_CS      : OUT STD_LOGIC;
    SPI_SCLK    : IN STD_LOGIC;
    SPI_MOSI    : OUT STD_LOGIC;
    SPI_MISO    : IN STD_LOGIC;
    SPI_RDY     : IN STD_LOGIC);
END MSXPi;



architecture rtl of MSXPi is
constant MSXPIVer : STD_LOGIC_VECTOR(3 DOWNTO 0) := "1011";
constant CTRLPORT1: STD_LOGIC_VECTOR(7 downto 0) := x"56";
constant CTRLPORT2: STD_LOGIC_VECTOR(7 downto 0) := x"57";
constant CTRLPORT3: STD_LOGIC_VECTOR(7 downto 0) := x"58";
constant CTRLPORT4: STD_LOGIC_VECTOR(7 downto 0) := x"59";
constant DATAPORT1: STD_LOGIC_VECTOR(7 downto 0) := x"5A";
constant DATAPORT2: STD_LOGIC_VECTOR(7 downto 0) := x"5B";
constant DATAPORT3: STD_LOGIC_VECTOR(7 downto 0) := x"5C";
constant DATAPORT4: STD_LOGIC_VECTOR(7 downto 0) := x"5D";

   signal csPinSignal	: std_logic;
	signal D_buff_pi		: std_logic_vector(7 downto 0);
	signal D_buff_msx		: std_logic_vector(7 downto 0);
	signal waitSignal		: STD_LOGIC := 'Z';
	signal msxwrite_s		: STD_LOGIC;
	signal msxread_s		: STD_LOGIC;
	signal spi_count_s	: std_logic_vector(3 downto 0) := "0000";
	signal spi_rdysignal	: std_logic;
	
	signal RPI_Recv_Data: std_logic_vector(7 downto 0);
    
begin
  
   spi_rdysignal <= SPI_RDY;
	csPinSignal <= msxwrite_s and msxread_s and not spi_rdysignal;
	SPI_CS <= csPinSignal;
	WAIT_n <= csPinSignal when csPinSignal = '0' else 'Z';
		
	msxwrite_s <= '0' when IORQ_n ='0' and WR_n = '0' and A = DATAPORT1 else '1';
	msxread_s <= '0' when IORQ_n ='0' and RD_n = '0' and (A = DATAPORT1 or A = CTRLPORT1) else '1';
	
	D_buff_msx <= D when msxwrite_s = '0' and A = DATAPORT1;
	D <= D_buff_pi when msxread_s = '0' and A = DATAPORT1 else
        SPI_RDY & csPinSignal & "11" & MSXPIVer when msxread_s = '0' and A = CTRLPORT1 else
		  "ZZZZZZZZ";

process(SPI_SCLK)
variable D_reg : std_logic_vector(7 downto 0);
begin
	if rising_edge(SPI_SCLK) then
	   if to_integer(unsigned(spi_count_s)) = 0 then
			D_reg := D_buff_msx;
		end if;
		if to_integer(unsigned(spi_count_s)) < 8 then
			D_buff_pi <= D_buff_pi(6 downto 0) & SPI_MISO;
			SPI_MOSI <= D_reg(7);
			
			-- start:testonly
			RPI_Recv_Data <= RPI_Recv_Data(6 downto 0) & D_reg(7);
			-- end:testonly
			
			D_reg(7 downto 1) := D_reg(6 downto 0);
			spi_count_s <= std_logic_vector(to_unsigned(to_integer(unsigned(spi_count_s)) + 1, 4));
		else
			spi_count_s <= "0000";
		end if;
	end if;
	
end process;

end rtl;

hardware/CPLD_Project/Sim/msxpi_readversion_tb.vhd
library ieee ;
use ieee.std_logic_1164.all; 
use ieee.numeric_std.all;

entity msxpi_tb is
end msxpi_tb;

architecture tb of msxpi_tb is
	component MSXPi is
		port (
			d			: inout std_logic_vector(7 downto 0);
			a			: in std_logic_vector(7 downto 0);
			iorq_n		: in std_logic;
			rd_n		: in std_logic;
			wr_n		: in std_logic;
			wait_n		: out std_logic;
			busdir_n	: out std_logic;
			spi_cs		: out std_logic;
			spi_sclk	: in std_logic;
			spi_mosi	: out std_logic;
			spi_miso	: in std_logic;
			spi_rdy  	: in std_logic);
	end component;

	signal a_s		 	: std_logic_vector(7 downto 0);
	signal d_s	 	    : std_logic_vector(7 downto 0);
	signal iorq_n_s		: std_logic;
	signal rd_n_s		: std_logic;
	signal wr_n_s		: std_logic;
	signal wait_n_s		: std_logic;
	signal busdir_n_s	: std_logic;
	signal spi_cs_s 	: std_logic;
	signal spi_clk_s	: std_logic;
	signal spi_mosi_s	: std_logic;
	signal spi_miso_s	: std_logic;
	signal rpi_rdy_s	: std_logic;

begin

	msxpi_instance: MSXPi
		port map(
			d => d_s,
			a => a_s,
			iorq_n => iorq_n_s,
			rd_n => rd_n_s,
			wr_n => wr_n_s,
			wait_n => wait_n_s,
			busdir_n => busdir_n_s,
			spi_cs => spi_cs_s,
			spi_sclk => spi_clk_s,
			spi_mosi => spi_mosi_s,
			spi_miso => spi_miso_S,
			spi_rdy => rpi_rdy_s);

	process
	begin
		
		spi_clk_s <= 'U';
		wr_n_s <= 'U';
		rd_n_s <= 'U';
		iorq_n_s <= 'U';
		rpi_rdy_s <= '0';
		wait for 2 ns;

-- ---------------------------------------
-- Simulate IO Read operation on port 5A

		a_s <= x"56";
		wr_n_s <= '1';
		rd_n_s <= '0';
		iorq_n_s <= '0';
		wait for 2 ns;

-- Simulate RPi enabling Busy Signal (SPI_RDY = 1)

		rpi_rdy_s <= '1';
		wait for 2 ns;
		
-- simulate RPi sending clock signal (SPI_SCLK)
	
		spi_clk_s <= '1';
		wait for 2 ns;

		spi_clk_s <= '0';
		wait for 2 ns;
		
		spi_miso_S <= '1';
		spi_clk_s <= '1';
		wait for 2 ns;

		spi_clk_s <= '0';
		wait for 2 ns;

		spi_miso_S <= '0';
		spi_clk_s <= '1';
		wait for 2 ns;

		spi_clk_s <= '0';
		wait for 2 ns;
		
		spi_miso_S <= '1';
		spi_clk_s <= '1';
		wait for 2 ns;

		spi_clk_s <= '0';
		wait for 2 ns;

		spi_miso_S <= '0';
		spi_clk_s <= '1';
		wait for 2 ns;

		spi_clk_s <= '0';
		wait for 2 ns;

		spi_miso_S <= '1';
		spi_clk_s <= '1';
		wait for 2 ns;

		spi_clk_s <= '0';
		wait for 2 ns;
		
		spi_miso_S <= '0';
		spi_clk_s <= '1';
		wait for 2 ns;

		spi_clk_s <= '0';
		wait for 2 ns;
		
		spi_miso_S <= '1';
		spi_clk_s <= '1';
		wait for 2 ns;

		spi_clk_s <= '0';
		wait for 2 ns;
	
		spi_miso_S <= '0';
		spi_clk_s <= '1';
		wait for 2 ns;

		spi_clk_s <= '0';
		wait for 2 ns;

-- 1 tick to allow CPLD to latch data in D Bus
		spi_clk_s <= '1';
		wait for 2 ns;

		spi_clk_s <= '0';
		wait for 2 ns;
		
		rpi_rdy_s <= '0';
		wait for 2 ns;
		
		wr_n_s <= '1';
		rd_n_s <= '1';
		iorq_n_s <= '1';
		wait for 2 ns;

-- ---------------------------------------
-- Simulate IO Read operation on port 5A

		a_s <= x"5A";
		wr_n_s <= '1';
		rd_n_s <= '0';
		iorq_n_s <= '0';
		wait for 2 ns;

-- Simulate RPi enabling Busy Signal (SPI_RDY = 1)

		rpi_rdy_s <= '1';
		wait for 2 ns;
		
-- simulate RPi sending clock signal (SPI_SCLK)
	
		spi_clk_s <= '1';
		wait for 2 ns;

		spi_clk_s <= '0';
		wait for 2 ns;
		
		spi_miso_S <= '1';
		spi_clk_s <= '1';
		wait for 2 ns;

		spi_clk_s <= '0';
		wait for 2 ns;

		spi_miso_S <= '0';
		spi_clk_s <= '1';
		wait for 2 ns;

		spi_clk_s <= '0';
		wait for 2 ns;
		
		spi_miso_S <= '1';
		spi_clk_s <= '1';
		wait for 2 ns;

		spi_clk_s <= '0';
		wait for 2 ns;

		spi_miso_S <= '1';
		spi_clk_s <= '1';
		wait for 2 ns;

		spi_clk_s <= '0';
		wait for 2 ns;

		spi_miso_S <= '1';
		spi_clk_s <= '1';
		wait for 2 ns;

		spi_clk_s <= '0';
		wait for 2 ns;
		
		spi_miso_S <= '0';
		spi_clk_s <= '1';
		wait for 2 ns;

		spi_clk_s <= '0';
		wait for 2 ns;
		
		spi_miso_S <= '1';
		spi_clk_s <= '1';
		wait for 2 ns;

		spi_clk_s <= '0';
		wait for 2 ns;
	
		spi_miso_S <= '1';
		spi_clk_s <= '1';
		wait for 2 ns;

		spi_clk_s <= '0';
		wait for 2 ns;

-- 1 tick to allow CPLD to latch data in D Bus
		spi_clk_s <= '1';
		wait for 2 ns;

		spi_clk_s <= '0';
		wait for 2 ns;
		
		rpi_rdy_s <= '0';
		wait for 2 ns;
		
		wr_n_s <= '1';
		rd_n_s <= '1';
		iorq_n_s <= '1';
		wait for 2 ns;
		
		wait;

	end process;
end;

hardware/CPLD_Project/Sim/msxpi_tb.vcd
$date
  Thu Dec 22 14:39:55 2022
$end
$version
  GHDL v0
$end
$timescale
  1 fs
$end
$scope module standard $end
$upscope $end
$scope module std_logic_1164 $end
$upscope $end
$scope module numeric_std $end
$upscope $end
$scope module msxpi_tb $end
$var reg 8 ! a_s[7:0] $end
$var reg 8 " d_s[7:0] $end
$var reg 1 # iorq_n_s $end
$var reg 1 $ rd_n_s $end
$var reg 1 % wr_n_s $end
$var reg 1 & wait_n_s $end
$var reg 1 ' busdir_n_s $end
$var reg 1 ( spi_cs_s $end
$var reg 1 ) spi_clk_s $end
$var reg 1 * spi_mosi_s $end
$var reg 1 + spi_miso_s $end
$var reg 1 , rpi_rdy_s $end
$scope module msxpi_instance $end
$var reg 8 - d[7:0] $end
$var reg 8 . a[7:0] $end
$var reg 1 / iorq_n $end
$var reg 1 0 rd_n $end
$var reg 1 1 wr_n $end
$var reg 1 2 busdir_n $end
$var reg 1 3 wait_n $end
$var reg 1 4 spi_cs $end
$var reg 1 5 spi_sclk $end
$var reg 1 6 spi_mosi $end
$var reg 1 7 spi_miso $end
$var reg 1 8 spi_rdy $end
$var reg 1 9 cspinsignal $end
$var reg 8 : d_buff_pi[7:0] $end
$var reg 8 ; d_buff_msx[7:0] $end
$var reg 1 < waitsignal $end
$var reg 1 = msxwrite_s $end
$var reg 1 > msxread_s $end
$var reg 4 ? spi_count_s[3:0] $end
$var reg 1 @ spi_rdysignal $end
$var reg 8 A rpi_recv_data[7:0] $end
$upscope $end
$upscope $end
$enddefinitions $end
#0
bUUUUUUUU !
bZZZZZZZZ "
U#
U$
U%
Z&
U'
1(
U)
U*
U+
0,
bZZZZZZZZ -
bUUUUUUUU .
U/
U0
U1
U2
Z3
14
U5
U6
U7
08
19
bUUUUUUUU :
bUUUUUUUU ;
Z<
1=
1>
b0000 ?
0@
bUUUUUUUU A
#2000000
b01010110 !
b00111011 "
0#
0$
1%
0&
0(
b00111011 -
b01010110 .
0/
00
11
03
04
09
0>
#4000000
b10111011 "
1,
b10111011 -
18
1@
#6000000
1)
15
#8000000
0)
05
#10000000
1)
1+
15
17
bUUUUUUU1 :
b0001 ?
#12000000
0)
05
#14000000
1)
0+
15
07
bUUUUUU10 :
b0010 ?
#16000000
0)
05
#18000000
1)
1+
15
17
bUUUUU101 :
b0011 ?
#20000000
0)
05
#22000000
1)
0+
15
07
bUUUU1010 :
b0100 ?
#24000000
0)
05
#26000000
1)
1+
15
17
bUUU10101 :
b0101 ?
#28000000
0)
05
#30000000
1)
0+
15
07
bUU101010 :
b0110 ?
#32000000
0)
05
#34000000
1)
1+
15
17
bU1010101 :
b0111 ?
#36000000
0)
05
#38000000
1)
0+
15
07
b10101010 :
b1000 ?
#40000000
0)
05
#42000000
1)
15
b0000 ?
#44000000
0)
05
#46000000
b00111011 "
0,
b00111011 -
08
0@
#48000000
bZZZZZZZZ "
1#
1$
Z&
1(
bZZZZZZZZ -
1/
10
Z3
14
19
1>
#50000000
b01011010 !
b10101010 "
0#
0$
0&
0(
b10101010 -
b01011010 .
0/
00
03
04
09
0>
#52000000
1,
18
1@
#54000000
b01010100 "
1)
b01010100 -
15
b01010100 :
b0001 ?
#56000000
0)
05
#58000000
b10101001 "
1)
1+
b10101001 -
15
17
b10101001 :
b0010 ?
#60000000
0)
05
#62000000
b01010010 "
1)
0+
b01010010 -
15
07
b01010010 :
b0011 ?
#64000000
0)
05
#66000000
b10100101 "
1)
1+
b10100101 -
15
17
b10100101 :
b0100 ?
#68000000
0)
05
#70000000
b01001011 "
1)
b01001011 -
15
b01001011 :
b0101 ?
#72000000
0)
05
#74000000
b10010111 "
1)
b10010111 -
15
b10010111 :
b0110 ?
#76000000
0)
05
#78000000
b00101110 "
1)
0+
b00101110 -
15
07
b00101110 :
b0111 ?
#80000000
0)
05
#82000000
b01011101 "
1)
1+
b01011101 -
15
17
b01011101 :
b1000 ?
#84000000
0)
05
#86000000
1)
15
b0000 ?
#88000000
0)
05
#90000000
b10111011 "
1)
b10111011 -
15
b10111011 :
b0001 ?
#92000000
0)
05
#94000000
0,
08
0@
#96000000
bZZZZZZZZ "
1#
1$
Z&
1(
bZZZZZZZZ -
1/
10
Z3
14
19
1>
