hardware/CPLD_Project/MSXPi.vhd
-- MSXPi Interface - Fully Quartus-Compatible
-- Version 1.1 Optimized
-- Author: Ronivon Costa
-- License: MIT

library ieee;
use ieee.std_logic_1164.all;
use ieee.numeric_std.all;
use work.msxpi_package.all;

entity MSXPi is
    port(
        D        : inout std_logic_vector(7 downto 0);
        A        : in    std_logic_vector(7 downto 0);
        IORQ_n   : in    std_logic;
        RD_n     : in    std_logic;
        WR_n     : in    std_logic;
        BUSDIR_n : out   std_logic;
        WAIT_n   : out   std_logic;
        SPI_CS   : out   std_logic;
        SPI_SCLK : in    std_logic;
        SPI_MOSI : out   std_logic;
        SPI_MISO : in    std_logic;
        SPI_RDY  : in    std_logic
    );
end MSXPi;

architecture rtl of MSXPi is

    -- SPI FSM
    type fsm_type is (idle, transferring);
    signal spi_state    : fsm_type := idle;

    -- Control signals
    signal readoper     : std_logic;
    signal writeoper    : std_logic;
    signal spi_en       : std_logic;
    signal reset_req    : std_logic;

    -- Buffers
    signal D_buff_msx   : std_logic_vector(7 downto 0);
    signal D_buff_pi    : std_logic_vector(7 downto 0);
    signal D_shift      : std_logic_vector(7 downto 0);

    -- SPI counter
    signal bit_count    : unsigned(2 downto 0) := "000";

    -- SPI busy flag
    signal SPI_busy     : std_logic := '0';

    -- SPI_RDY for MSX
    signal SPI_RDY_s    : std_logic;

    -- Port mask functions
    function is_ctrl_port(addr : std_logic_vector(7 downto 0)) return boolean is
    begin
        return (addr(7 downto 4) = "0101") and (unsigned(addr(3 downto 0)) <= 9);
    end function;

    function is_data_port(addr : std_logic_vector(7 downto 0)) return boolean is
    begin
        return (addr(7 downto 4) = "0101") and 
               (unsigned(addr(3 downto 0)) >= 10) and 
               (unsigned(addr(3 downto 0)) <= 13);
    end function;

begin

    -- Read/Write detection
    readoper  <= not (IORQ_n or RD_n);
    writeoper <= not (IORQ_n or WR_n);

    -- SPI enable (using boolean functions)
    spi_en <= '1' when writeoper = '1' and (is_ctrl_port(A) or is_data_port(A)) else '0';

    -- BUS direction
    BUSDIR_n <= '0' when readoper = '1' and (is_ctrl_port(A) or is_data_port(A)) else '1';

    -- SPI_RDY output
    SPI_RDY_s <= SPI_busy or not SPI_RDY;

    -- Data output to MSX
    D <= "0000000" & SPI_RDY_s          when readoper = '1' and A = CTRLPORT1 else
         D_buff_pi                      when readoper = '1' and is_data_port(A) else
         "0000" & MSXPIVer              when readoper = '1' and A = CTRLPORT2 else
         "ZZZZZZZZ";

    -- Latch written MSX data
    process(writeoper, D, A)
    begin
        if writeoper = '1' and (is_ctrl_port(A) or is_data_port(A)) then
            D_buff_msx <= D;
        end if;
    end process;

    -- Reset request (bitwise comparison to avoid Quartus errors)
    reset_req <= '1' when writeoper = '1' and A = CTRLPORT1 and D = "11111111" else '0';

    -- SPI FSM
    process(SPI_SCLK, reset_req)
    begin
        if reset_req = '1' then
            SPI_busy   <= '0';
            D_buff_pi  <= (others => '0');
            spi_state  <= idle;
            bit_count  <= (others => '0');
            D_shift    <= (others => '0');
            SPI_MOSI   <= '0';
        elsif rising_edge(SPI_SCLK) then
            case spi_state is
                when idle =>
                    if spi_en = '1' then
                        SPI_busy  <= '1';
                        D_shift   <= D_buff_msx;
                        bit_count <= (others => '0');
                        spi_state <= transferring;
                    else
                        SPI_busy <= '0';
                    end if;

                when transferring =>
                    SPI_MOSI        <= D_shift(7);
                    D_shift(6 downto 0) <= D_shift(7 downto 1);
                    D_buff_pi       <= D_buff_pi(6 downto 0) & SPI_MISO;

                    bit_count       <= bit_count + 1;
                    if bit_count = "111" then
                        spi_state <= idle;
                        SPI_busy  <= '0';
                    end if;
            end case;
        end if;
    end process;

    -- SPI CS output
    SPI_CS <= not SPI_busy;

    -- WAIT_n tri-state for MSX bus
    WAIT_n <= 'Z';

end rtl;

hardware/CPLD_Project/tb_MSXPi.vhd
-- MSXPi Testbench for GTKWave
-- Author: Ronivon Costa
-- License: MIT

library ieee;
use ieee.std_logic_1164.all;
use ieee.numeric_std.all;
use work.msxpi_package.all;

entity tb_MSXPi is
-- Testbench has no ports
end tb_MSXPi;

architecture sim of tb_MSXPi is

    -- Component under test
    component MSXPi is
        port(
            D        : inout std_logic_vector(7 downto 0);
            A        : in    std_logic_vector(7 downto 0);
            IORQ_n   : in    std_logic;
            RD_n     : in    std_logic;
            WR_n     : in    std_logic;
            BUSDIR_n : out   std_logic;
            WAIT_n   : out   std_logic;
            SPI_CS   : out   std_logic;
            SPI_SCLK : in    std_logic;
            SPI_MOSI : out   std_logic;
            SPI_MISO : in    std_logic;
            SPI_RDY  : in    std_logic
        );
    end component;

    -- Signals
    signal D        : std_logic_vector(7 downto 0) := (others => '0');
    signal A        : std_logic_vector(7 downto 0) := (others => '0');
    signal IORQ_n   : std_logic := '1';
    signal RD_n     : std_logic := '1';
    signal WR_n     : std_logic := '1';
    signal BUSDIR_n : std_logic;
    signal WAIT_n   : std_logic;
    signal SPI_CS   : std_logic;
    signal SPI_SCLK : std_logic := '0';
    signal SPI_MOSI : std_logic;
    signal SPI_MISO : std_logic := '0';
    signal SPI_RDY  : std_logic := '1';

    -- Clock period
    constant CLK_PERIOD : time := 100 ns;

begin

    -- Instantiate DUT
    DUT: MSXPi
        port map(
            D        => D,
            A        => A,
            IORQ_n   => IORQ_n,
            RD_n     => RD_n,
            WR_n     => WR_n,
            BUSDIR_n => BUSDIR_n,
            WAIT_n   => WAIT_n,
            SPI_CS   => SPI_CS,
            SPI_SCLK => SPI_SCLK,
            SPI_MOSI => SPI_MOSI,
            SPI_MISO => SPI_MISO,
            SPI_RDY  => SPI_RDY
        );

    -- SPI Clock Generation
    clk_proc: process
    begin
        while true loop
            SPI_SCLK <= '0';
            wait for CLK_PERIOD / 2;
            SPI_SCLK <= '1';
            wait for CLK_PERIOD / 2;
        end loop;
    end process;

    -- Stimulus process
    stim_proc: process
    begin
        -- Initial delay
        wait for 200 ns;

        -- Write 0xFF to CTRLPORT1 (should trigger reset)
        A      <= CTRLPORT1;
        D      <= "11111111";
        IORQ_n <= '0';
        WR_n   <= '0';
        wait for CLK_PERIOD;
        IORQ_n <= '1';
        WR_n   <= '1';
        wait for CLK_PERIOD;

        -- Write some data to DATAPORT1
        A      <= DATAPORT1;
        D      <= "10101010";
        IORQ_n <= '0';
        WR_n   <= '0';
        wait for CLK_PERIOD;
        IORQ_n <= '1';
        WR_n   <= '1';
        wait for CLK_PERIOD;

        -- Read CTRLPORT1
        A    <= CTRLPORT1;
        IORQ_n <= '0';
        RD_n   <= '0';
        wait for CLK_PERIOD;
        IORQ_n <= '1';
        RD_n   <= '1';
        wait for CLK_PERIOD;

        -- Simulate SPI MISO data
        SPI_MISO <= '1';
        wait for CLK_PERIOD;
        SPI_MISO <= '0';
        wait for CLK_PERIOD;

        -- End simulation
        wait for 1 us;
        assert false report "End of simulation" severity note;
        wait;
    end process;

end sim;

hardware/CPLD_Project/tb_MSXPi.vcd
$date
  Sat Aug 30 22:54:03 2025
$end
$version
  GHDL v0
$end
$timescale
  1 fs
$end
$scope module standard $end
$upscope $end
$scope module std_logic_1164 $end
$upscope $end
$scope module numeric_std $end
$upscope $end
$scope module msxpi_package $end
$upscope $end
$scope module tb_msxpi $end
$var reg 8 ! d[7:0] $end
$var reg 8 " a[7:0] $end
$var reg 1 # iorq_n $end
$var reg 1 $ rd_n $end
$var reg 1 % wr_n $end
$var reg 1 & busdir_n $end
$var reg 1 ' wait_n $end
$var reg 1 ( spi_cs $end
$var reg 1 ) spi_sclk $end
$var reg 1 * spi_mosi $end
$var reg 1 + spi_miso $end
$var reg 1 , spi_rdy $end
$scope module dut $end
$var reg 8 - d[7:0] $end
$var reg 8 . a[7:0] $end
$var reg 1 / iorq_n $end
$var reg 1 0 rd_n $end
$var reg 1 1 wr_n $end
$var reg 1 2 busdir_n $end
$var reg 1 3 wait_n $end
$var reg 1 4 spi_cs $end
$var reg 1 5 spi_sclk $end
$var reg 1 6 spi_mosi $end
$var reg 1 7 spi_miso $end
$var reg 1 8 spi_rdy $end
$comment spi_state is not handled $end
$var reg 1 9 readoper $end
$var reg 1 : writeoper $end
$var reg 1 ; spi_en $end
$var reg 1 < reset_req $end
$var reg 8 = d_buff_msx[7:0] $end
$var reg 8 > d_buff_pi[7:0] $end
$var reg 8 ? d_shift[7:0] $end
$var reg 3 @ bit_count[2:0] $end
$var reg 1 A spi_busy $end
$var reg 1 B spi_rdy_s $end
$upscope $end
$upscope $end
$enddefinitions $end
#0
b00000000 !
b00000000 "
1#
1$
1%
1&
Z'
1(
0)
U*
0+
1,
b00000000 -
b00000000 .
1/
10
11
12
Z3
14
05
U6
07
18
09
0:
0;
0<
bUUUUUUUU =
bUUUUUUUU >
bUUUUUUUU ?
b000 @
0A
0B
#50000000
1)
15
#100000000
0)
05
#150000000
1)
15
#200000000
b11111111 !
b01010110 "
0#
0%
0)
0*
b11111111 -
b01010110 .
0/
01
05
06
1:
1;
1<
b11111111 =
b00000000 >
b00000000 ?
#250000000
1)
15
#300000000
1#
1%
0)
1/
11
05
0:
0;
0<
#350000000
1)
15
#400000000
b10101010 !
b01011010 "
0#
0%
0)
b10101010 -
b01011010 .
0/
01
05
1:
1;
b10101010 =
#450000000
0(
1)
04
15
b10101010 ?
1A
1B
#500000000
1#
1%
0)
1/
11
05
0:
0;
#550000000
1)
1*
15
16
b11010101 ?
b001 @
#600000000
bX0X0X0XX !
b01010110 "
0#
0$
0&
0)
bX0X0X0XX -
b01010110 .
0/
00
02
05
19
#650000000
1)
15
b11101010 ?
b010 @
#700000000
b10101010 !
1#
1$
1&
0)
b10101010 -
1/
10
12
05
09
#750000000
1)
15
b11110101 ?
b011 @
#800000000
0)
1+
05
17
#850000000
1)
15
b00000001 >
b11111010 ?
b100 @
#900000000
0)
0+
05
07
#950000000
1)
15
b00000010 >
b11111101 ?
b101 @
#1000000000
0)
05
#1050000000
1)
15
b00000100 >
b11111110 ?
b110 @
#1100000000
0)
05
#1150000000
1)
15
b00001000 >
b11111111 ?
b111 @
#1200000000
0)
05
#1250000000
1(
1)
14
15
b00010000 >
b000 @
0A
0B
